streamlit_stacker/__init__.py
streamlit_stacker/components.json
streamlit_stacker/components.py
streamlit_stacker/echo.py
streamlit_stacker/st_stacker.py
streamlit_stacker-0.0.6.dist-info/LICENSE
streamlit_stacker-0.0.6.dist-info/METADATA
streamlit_stacker-0.0.6.dist-info/WHEEL
streamlit_stacker-0.0.6.dist-info/top_level.txt
streamlit_stacker-0.0.6.dist-info/RECORD
