Metadata-Version: 2.1
Name: streamlit_stacker
Version: 0.0.6
Summary: Tool allowing to stack streamlit commands and resolve them in a controlable manner.
Home-page: https://github.com/B4PT0R/streamlit_stacker
Author: Baptiste Ferrand
Author-email: bferrand.maths@gmail.com
License-File: LICENSE
Requires-Dist: streamlit >=1.30.0
Requires-Dist: streamlit-modal-input
Requires-Dist: streamlit-pdf-reader
